aionetiface/__init__.py
aionetiface/__main__.py
aionetiface/config.py
aionetiface/do_imports.py
aionetiface/entrypoint.py
aionetiface/errors.py
aionetiface/install.py
aionetiface/settings.py
aionetiface/net/address.py
aionetiface/net/daemon.py
aionetiface/net/ip_range.py
aionetiface/net/keep_alive.py
aionetiface/net/net_defs.py
aionetiface/net/net_patterns.py
aionetiface/net/net_utils.py
aionetiface/net/selector_proxy.py
aionetiface/net/socket.py
aionetiface/net/asyncio/__init__.py
aionetiface/net/asyncio/async_run.py
aionetiface/net/asyncio/asyncio_patches.py
aionetiface/net/asyncio/event_loop.py
aionetiface/net/bind/__init__.py
aionetiface/net/bind/bind.py
aionetiface/net/bind/bind_rules.py
aionetiface/net/bind/bind_utils.py
aionetiface/net/pipe/__init__.py
aionetiface/net/pipe/pipe.py
aionetiface/net/pipe/pipe_client.py
aionetiface/net/pipe/pipe_defs.py
aionetiface/net/pipe/pipe_events.py
aionetiface/net/pipe/pipe_tcp_events.py
aionetiface/net/pipe/pipe_utils.py
aionetiface/nic/__init__.py
aionetiface/nic/default_interface.py
aionetiface/nic/interface.py
aionetiface/nic/interface_utils.py
aionetiface/nic/load_interface.py
aionetiface/nic/select_interface.py
aionetiface/nic/nat/__init__.py
aionetiface/nic/nat/nat_defs.py
aionetiface/nic/nat/nat_predict.py
aionetiface/nic/nat/nat_test.py
aionetiface/nic/nat/nat_utils.py
aionetiface/nic/netifaces/__init__.py
aionetiface/nic/netifaces/netiface_extra.py
aionetiface/nic/netifaces/netiface_fallback.py
aionetiface/nic/netifaces/windows/__init__.py
aionetiface/nic/netifaces/windows/win_net.py
aionetiface/nic/netifaces/windows/win_netifaces.py
aionetiface/nic/netifaces/windows/win_netsh.py
aionetiface/nic/netifaces/windows/win_wmic.py
aionetiface/nic/route/__init__.py
aionetiface/nic/route/route.py
aionetiface/nic/route/route_load.py
aionetiface/nic/route/route_pool.py
aionetiface/nic/route/route_table.py
aionetiface/nic/route/route_utils.py
aionetiface/protocol/__init__.py
aionetiface/protocol/ack_udp.py
aionetiface-0.0.10.dist-info/licenses/LICENSE
aionetiface-0.0.10.dist-info/METADATA
aionetiface-0.0.10.dist-info/WHEEL
aionetiface-0.0.10.dist-info/top_level.txt
aionetiface-0.0.10.dist-info/RECORD
