Metadata-Version: 2.4
Name: aionetiface
Version: 0.0.10
Summary: Asynchronous networking library 
Home-page: http://github.com/robertsdotpm/aionetiface
Author: Matthew Roberts
Author-email: matthew@roberts.pm
License: public domain
Keywords: test,python
Classifier: Intended Audience :: Developers
Classifier: Programming Language :: Python :: 3
License-File: LICENSE
Requires-Dist: ntplib
Requires-Dist: ecdsa
Requires-Dist: netifaces; platform_system != "Windows"
Requires-Dist: pyroute2; platform_system == "Linux"
Requires-Dist: winregistry; platform_system == "Windows"
Dynamic: author
Dynamic: author-email
Dynamic: classifier
Dynamic: description
Dynamic: description-content-type
Dynamic: home-page
Dynamic: keywords
Dynamic: license
Dynamic: license-file
Dynamic: requires-dist
Dynamic: summary
